comrad/__init__.py
comrad/app/__init__.py
comrad/app/app.py
comrad/app/components.py
comrad/app/controller.py
comrad/app/exceptions.py
comrad/app/page.py
comrad/app/view.py
comrad/util/__init__.py
comrad/util/code.py
pyodide_dill/__init__.py
comrad-0.0.1.dist-info/entry_points.txt
comrad-0.0.1.dist-info/WHEEL
comrad-0.0.1.dist-info/METADATA
comrad-0.0.1.dist-info/RECORD
