Metadata-Version: 2.1
Name: comrad
Version: 0.0.1
Summary: A framework for quickly deploying simple Python applications.
License: MIT
Author: Kaj Siebert
Author-email: kaj@k-si.com
Requires-Python: >=3.8,<4.0
Classifier: License :: OSI Approved :: MIT License
Classifier: Programming Language :: Python :: 3
Classifier: Programming Language :: Python :: 3.8
Classifier: Programming Language :: Python :: 3.9
Classifier: Programming Language :: Python :: 3.10
Classifier: Programming Language :: Python :: 3.11
Provides-Extra: examples
Provides-Extra: jupyter
Provides-Extra: pyodide
Provides-Extra: web
Requires-Dist: dill (>=0.3.6,<0.4.0)
Requires-Dist: flask (>=2.2.2,<3.0.0); extra == "web"
Requires-Dist: flask-cors (>=3.0.10,<4.0.0); extra == "web"
Requires-Dist: jinja2 (>=3.1.2,<4.0.0)
Requires-Dist: jupyterlab (>=3.6.0,<4.0.0); extra == "jupyter"
Requires-Dist: matplotlib (>=3.5.2,<4.0.0); extra == "jupyter"
Requires-Dist: numpy (>=1.23.5,<2.0.0); extra == "examples"
Requires-Dist: openpyxl (>=3.1.0,<4.0.0); extra == "jupyter" or extra == "pyodide"
Requires-Dist: pandas (>=1.5.2,<2.0.0); extra == "examples"
Requires-Dist: plotly (>=5.13.0,<6.0.0); extra == "jupyter" or extra == "pyodide"
Requires-Dist: prpc-python[cli] (>=0.9.1,<0.10.0)
Requires-Dist: pydantic (>=1.10.4,<2.0.0)
Requires-Dist: pyyaml (>=6.0,<7.0)
Requires-Dist: tqdm (>=4.64.1,<5.0.0); extra == "jupyter"
